textract/__init__.py
textract/cli.py
textract/colors.py
textract/exceptions.py
textract/parsers/__init__.py
textract/parsers/audio.py
textract/parsers/csv_parser.py
textract/parsers/doc_parser.py
textract/parsers/docx_parser.py
textract/parsers/eml_parser.py
textract/parsers/epub_parser.py
textract/parsers/gif_parser.py
textract/parsers/html_parser.py
textract/parsers/image.py
textract/parsers/jpg_parser.py
textract/parsers/json_parser.py
textract/parsers/mp3_parser.py
textract/parsers/msg_parser.py
textract/parsers/odt_parser.py
textract/parsers/ogg_parser.py
textract/parsers/pdf_parser.py
textract/parsers/png_parser.py
textract/parsers/pptx_parser.py
textract/parsers/ps_parser.py
textract/parsers/psv_parser.py
textract/parsers/rtf_parser.py
textract/parsers/tiff_parser.py
textract/parsers/tsv_parser.py
textract/parsers/txt_parser.py
textract/parsers/utils.py
textract/parsers/wav_parser.py
textract/parsers/xls_parser.py
textract/parsers/xlsx_parser.py
textract-1.6.5.data/scripts/textract
textract-1.6.5.dist-info/LICENSE
textract-1.6.5.dist-info/METADATA
textract-1.6.5.dist-info/WHEEL
textract-1.6.5.dist-info/top_level.txt
textract-1.6.5.dist-info/RECORD
