Metadata-Version: 2.1
Name: textract
Version: 1.6.5
Summary: extract text from any document. no muss. no fuss.
Home-page: https://github.com/deanmalmgren/textract
Download-URL: https://github.com/deanmalmgren/textract/archives/master
Author: Dean Malmgren
Author-email: dean.malmgren@datascopeanalytics.com
License: MIT
Platform: UNKNOWN
Provides-Extra: pocketsphinx
License-File: LICENSE
